{
  "attrs": {
    "pro": { "text": "PRO features", "type": "pro", "description": ["• Create and export lead lists" , "• Access company and contact details in all data products", "• CRM integration (HubSpot, Pipedrive)", "• More" ], "to": "/pro" },
    "users": { "text": "Users", "type": "number", "description": ["Number of users who can access the account with their own login."] },
    "credits": { "text": "Credits / mo", "type": "credits", "description": ["Credits can be spent on lead lists, technology lookups and APIs. See 'credit usage' below."] },
    "lists": { "text": "Lead lists", "type": "small", "description": ["Free lists include:", "• Lead lists (any technology, up to 500K sites)", "• Technology lookup (up to 100K sites)", "• Email verification (up to 100K addresses)", "", "Create more lists using the included credits. See 'credit usage' below."] },
    "lookups": { "text": "Technology lookups", "type": "string" },
    "apis": { "text": "API access", "type": "string" },
    "cancellation": { "text": "Anytime cancellation", "type": "string" },
    "support": { "text": "Support", "type": "small" }
  },
  "plans": {
    "credits_starter_v5_mo": {
      "name": "Starter",
      "interval": "month",
      "price": 14900,
      "attrs": {
        "credits": 5000,
        "users": 1,
        "support": ["Email"],
        "lookups": true,
        "lists": ["Use included credits"],
        "lookups": true,
        "apis": true,
        "pro": true,
        "cancellation": true
      }
    },
    "credits_team_v2_mo": {
      "name": "Team",
      "interval": "month",
      "raised": true,
      "price": 24900,
      "attrs": {
        "credits": 50000,
        "users": 5,
        "support": ["Email & phone"],
        "lookups": true,
        "lists": ["Use included credits", "+ 1 Free list / mo"],
        "apis": true,
        "pro": true,
        "cancellation": true
      }
    },
    "credits_business_v5_mo": {
      "name": "Business",
      "interval": "month",
      "price": 44900,
      "attrs": {
        "credits": 200000,
        "users": 15,
        "support": ["Priority email & phone"],
        "lookups": true,
        "lists": ["Use included credits", "+ 2 Free lists / mo"],
        "lookups": true,
        "apis": true,
        "pro": true,
        "cancellation": true
      }
    },
    "credits_enterprise_v1_mo": {
      "name": "Enterprise",
      "interval": "month",
      "price": 84900,
      "attrs": {
        "credits": 500000,
        "users": 50,
        "support": ["Dedicated account manager"],
        "lookups": true,
        "lists": ["Use included credits", "+ 3 Free lists / mo"],
        "apis": true,
        "pro": true,
        "cancellation": true
      }
    },
    "credits_starter_v7_yr": {
      "name": "Starter",
      "interval": "year",
      "price": 149000,
      "attrs": {
        "credits": 5000,
        "users": 1,
        "support": ["Email"],
        "lookups": true,
        "lists": ["Use included credits"],
        "lookups": true,
        "apis": true,
        "pro": true,
        "cancellation": true
      }
    },
    "credits_team_v3_yr": {
      "name": "Team",
      "interval": "year",
      "raised": true,
      "price": 249000,
      "attrs": {
        "credits": 50000,
        "users": 5,
        "support": ["Email & phone"],
        "lookups": true,
        "lists": ["Use included credits", "+ 1 Free list / mo"],
        "lookups": true,
        "apis": true,
        "pro": true,
        "cancellation": true
      }
    },
    "credits_business_v7_yr": {
      "name": "Business",
      "interval": "year",
      "price": 449000,
      "attrs": {
        "credits": 200000,
        "users": 15,
        "support": ["Priority email & phone"],
        "lookups": true,
        "lists": ["Use included credits", "+ 2 Free lists / mo"],
        "lookups": true,
        "apis": true,
        "pro": true,
        "cancellation": true
      }
    },
    "credits_enterprise_v1_yr": {
      "name": "Enterprise",
      "interval": "year",
      "price": 849000,
      "attrs": {
        "credits": 500000,
        "users": 50,
        "support": ["Dedicated account manager"],
        "lookups": true,
        "lists": ["Use included credits", "+ 3 Free lists / mo"],
        "apis": true,
        "pro": true,
        "cancellation": true
      }
    }
  }
}
